x_unet/__init__.py
x_unet/x_unet.py
x_unet-0.4.0.dist-info/LICENSE
x_unet-0.4.0.dist-info/METADATA
x_unet-0.4.0.dist-info/WHEEL
x_unet-0.4.0.dist-info/top_level.txt
x_unet-0.4.0.dist-info/RECORD
