Metadata-Version: 2.1
Name: x-unet
Version: 0.4.0
Summary: X-Unet
Home-page: https://github.com/lucidrains/x-unet
Author: Phil Wang
Author-email: lucidrains@gmail.com
License: MIT
Keywords: artificial intelligence,deep learning,biomedical segmentation,medical deep learning,unets
Classifier: Development Status :: 4 - Beta
Classifier: Intended Audience :: Developers
Classifier: Topic :: Scientific/Engineering :: Artificial Intelligence
Classifier: License :: OSI Approved :: MIT License
Classifier: Programming Language :: Python :: 3.6
License-File: LICENSE
Requires-Dist: beartype
Requires-Dist: einops >=0.4
Requires-Dist: torch >=1.6
